{
    "defaultSeverity": "error",
    // make sure "tslint-config-prettier" is at the end
    "extends": ["tslint:latest", "tslint-config-prettier"],
    "rules": {
        "deprecation": true,
        "no-implicit-dependencies": [true, "dev"],
        "no-submodule-imports": false,
        "eofline": false,
        "indent": false,
        "member-access": [true, "no-public"],
        "ordered-imports": [true],
        "max-line-length": [160],
        "member-ordering": [false],
        "curly": false,
        "interface-name": [false],
        "array-type": [false],
        "no-empty-interface": false,
        "prefer-conditional-expression": false,
        "no-empty": true,
        "arrow-parens": false,
        "object-literal-sort-keys": false,
        "no-unused-expression": false,
        "max-classes-per-file": [false],
        "variable-name": [false],
        "one-line": [false],
        "one-variable-per-declaration": [false],
        "promise-function-async": true,
        "no-null-keyword": true,
        "no-return-await": true,
        "match-default-export-name": true,
        "prefer-readonly": true,
        "typedef": [
            true,
            "call-signature",
            "arrow-call-signature",
            "parameter",
            "arrow-parameter",
            "property-declaration",
            "variable-declaration",
            "member-variable-declaration",
            "object-destructuring",
            "array-destructuring"
        ]
    },
    "rulesDirectory": []
}
